onlylog/__init__.py
onlylog/__version__.py
onlylog/onlylog.py
onlylog-1.0.1.dist-info/METADATA
onlylog-1.0.1.dist-info/WHEEL
onlylog-1.0.1.dist-info/top_level.txt
onlylog-1.0.1.dist-info/RECORD
